{"Imee\\Models\\Cms\\Lesscode\\LesscodeSchemaConfig":[{"id":127,"schema_json":"{\"form\":{\"labelCol\":6,\"wrapperCol\":12,\"name\":\"\\u793c\\u5305\\u914d\\u7f6e\",\"name_en\":\"\",\"filterCache\":0},\"schema\":{\"type\":\"object\",\"properties\":{\"o4ga1pvnk59\":{\"type\":\"void\",\"x-component\":\"Card\",\"x-component-props\":{\"title\":\"\\u5217\\u8868\",\"title_en\":\"list\",\"action\":\"list\",\"drive\":\"mysql\",\"pk\":\"bid\"},\"cardType\":\"list\",\"x-designable-id\":\"o4ga1pvnk59\",\"x-index\":0,\"properties\":{\"bid\":{\"title\":\"\\u793c\\u5305id\",\"title_en\":\"\",\"x-decorator\":\"FormItem\",\"x-component\":\"Input\",\"name\":\"bid\",\"x-designable-id\":\"k40vi1efwdq\",\"x-index\":0,\"type\":\"string\",\"hidden\":0,\"disabled\":0,\"required\":0,\"placeholder\":\"\",\"length\":255},\"cn\":{\"title\":\"\\u793c\\u5305\\u540d\\u79f0cn\",\"title_en\":\"\",\"x-decorator\":\"FormItem\",\"x-component\":\"Input\",\"name\":\"cn\",\"x-designable-id\":\"lb63j9a0unf\",\"x-index\":1,\"type\":\"string\",\"hidden\":0,\"disabled\":0,\"required\":0,\"placeholder\":\"\",\"length\":255},\"en\":{\"title\":\"\\u793c\\u5305\\u540d\\u79f0en\",\"title_en\":\"\",\"x-decorator\":\"FormItem\",\"x-component\":\"Input\",\"name\":\"en\",\"x-designable-id\":\"oserz1hkg8v\",\"x-index\":2,\"type\":\"string\",\"hidden\":0,\"disabled\":0,\"required\":0,\"placeholder\":\"\",\"length\":255},\"ar\":{\"title\":\"\\u793c\\u5305\\u540d\\u79f0ar\",\"title_en\":\"\",\"x-decorator\":\"FormItem\",\"x-component\":\"Input\",\"name\":\"ar\",\"x-designable-id\":\"tzrwj2vnx9i\",\"x-index\":3,\"type\":\"string\",\"hidden\":0,\"disabled\":0,\"required\":0,\"placeholder\":\"\",\"length\":255},\"reward_str\":{\"title\":\"\\u793c\\u5305\\u7269\\u54c1\",\"title_en\":\"\",\"x-decorator\":\"FormItem\",\"x-component\":\"Input\",\"name\":\"reward_str\",\"x-designable-id\":\"9mzxa31sj2h\",\"x-index\":4,\"type\":\"string\",\"hidden\":0,\"disabled\":0,\"required\":0,\"isHtml\":1,\"placeholder\":\"\",\"length\":255},\"remark\":{\"title\":\"\\u793c\\u5305\\u540e\\u53f0\\u5907\\u6ce8\",\"title_en\":\"\",\"x-decorator\":\"FormItem\",\"x-component\":\"Input\",\"name\":\"remark\",\"x-designable-id\":\"rdox4p60zyj\",\"x-index\":5,\"type\":\"string\",\"hidden\":0,\"disabled\":0,\"required\":0,\"placeholder\":\"\",\"length\":255},\"display_status\":{\"title\":\"\\u72b6\\u6001\",\"title_en\":\"\",\"x-decorator\":\"FormItem\",\"x-component\":\"Input\",\"name\":\"display_status\",\"x-designable-id\":\"hcws7trl0au\",\"x-index\":6,\"type\":\"string\",\"hidden\":0,\"disabled\":0,\"required\":0,\"placeholder\":\"\",\"length\":255}}},\"pu3wfc6a2b0\":{\"type\":\"void\",\"x-component\":\"Card\",\"x-component-props\":{\"title\":\"\\u7b5b\\u9009\",\"title_en\":\"filter\",\"action\":\"filter\"},\"cardType\":\"filter\",\"x-designable-id\":\"pu3wfc6a2b0\",\"x-index\":1,\"properties\":{\"bid\":{\"title\":\"\\u793c\\u5305id\",\"title_en\":\"\",\"x-decorator\":\"FormItem\",\"x-component\":\"Input\",\"name\":\"bid\",\"x-designable-id\":\"h1f8rut0od3\",\"x-index\":0,\"type\":\"string\",\"hidden\":0,\"disabled\":0,\"required\":0,\"placeholder\":\"\",\"length\":255},\"name\":{\"title\":\"\\u793c\\u5305\\u540d\\u79f0\",\"title_en\":\"\",\"x-decorator\":\"FormItem\",\"x-component\":\"Input\",\"name\":\"name\",\"x-designable-id\":\"ukwnrzhs7oa\",\"x-index\":1,\"type\":\"string\",\"placeholder\":\"\",\"length\":255},\"status\":{\"title\":\"\\u72b6\\u6001 \",\"title_en\":\"\",\"x-decorator\":\"FormItem\",\"x-component\":\"Select\",\"name\":\"status\",\"x-designable-id\":\"tlhe0xfpszr\",\"x-index\":2,\"type\":\"\",\"placeholder\":\"\",\"length\":255,\"service\":\"\\\\Imee\\\\Service\\\\Operate\\\\WelcomegiftbagService\",\"method\":\"getStatus\",\"params\":\"{\\\"params\\\":[null,\\\"label,value\\\"]}\"}}},\"z9crogmlwuf\":{\"type\":\"void\",\"x-component\":\"Card\",\"x-component-props\":{\"title\":\"\\u6dfb\\u52a0\\u793c\\u5305\",\"action\":\"action\",\"position\":\"createArea\",\"drive\":\"mysql\",\"btnForm\":\"text\",\"btnContent\":\"\\u6dfb\\u52a0\\u793c\\u5305\",\"modalId\":\"add_gift_bag\",\"url\":\"\\\/operate\\\/welcomegiftbag\\\/create\",\"params\":\"{\\\"params\\\":[[\\\"url\\\",\\\"\\\/operate\\\/welcomegiftbag\\\/create\\\"]]}\"},\"cardType\":\"manMadeModal\",\"x-designable-id\":\"z9crogmlwuf\",\"x-index\":2},\"e9fvh2bxagl\":{\"type\":\"void\",\"x-component\":\"Card\",\"x-component-props\":{\"title\":\"\\u7f16\\u8f91\",\"action\":\"operate\",\"position\":\"operateArea\",\"drive\":\"mysql\",\"btnForm\":\"text\",\"btnContent\":\"\\u7f16\\u8f91\",\"width\":640,\"show\":\"record.status == 0\",\"url\":\"\\\/operate\\\/welcomegiftbag\\\/modify\"},\"cardType\":\"modal\",\"x-designable-id\":\"e9fvh2bxagl\",\"x-index\":3,\"width\":640,\"properties\":{\"bid\":{\"title\":\"id\",\"title_en\":\"\",\"x-decorator\":\"FormItem\",\"x-component\":\"Input\",\"name\":\"bid\",\"x-designable-id\":\"nv1whm8rsp0\",\"x-index\":0,\"type\":\"string\",\"hidden\":1,\"disabled\":0,\"required\":1,\"writeback\":1,\"placeholder\":\"\",\"length\":255},\"cn\":{\"title\":\"\\u793c\\u5305\\u540d\\u79f0cn\",\"title_en\":\"\",\"x-decorator\":\"FormItem\",\"x-component\":\"Input\",\"name\":\"cn\",\"x-designable-id\":\"duh0oy76nrq\",\"x-index\":1,\"type\":\"string\",\"hidden\":0,\"disabled\":0,\"required\":1,\"writeback\":1,\"placeholder\":\"\",\"length\":255},\"en\":{\"title\":\"\\u793c\\u5305\\u540d\\u79f0en\",\"title_en\":\"\",\"x-decorator\":\"FormItem\",\"x-component\":\"Input\",\"name\":\"en\",\"x-designable-id\":\"34fhzyl1qk8\",\"x-index\":2,\"type\":\"string\",\"hidden\":0,\"disabled\":0,\"required\":1,\"writeback\":1,\"placeholder\":\"\",\"length\":255},\"ar\":{\"title\":\"\\u793c\\u5305\\u540d\\u79f0ar\",\"title_en\":\"\",\"x-decorator\":\"FormItem\",\"x-component\":\"Input\",\"name\":\"ar\",\"x-designable-id\":\"squ83yz1rei\",\"x-index\":3,\"type\":\"string\",\"hidden\":0,\"disabled\":0,\"required\":0,\"writeback\":1,\"placeholder\":\"\",\"length\":255},\"ms\":{\"title\":\"\\u793c\\u5305\\u540d\\u79f0ms\",\"title_en\":\"\",\"x-decorator\":\"FormItem\",\"x-component\":\"Input\",\"name\":\"ms\",\"x-designable-id\":\"7cflz4yobu9\",\"x-index\":4,\"type\":\"string\",\"hidden\":0,\"disabled\":0,\"required\":0,\"writeback\":1,\"placeholder\":\"\",\"length\":255},\"id\":{\"title\":\"\\u793c\\u5305\\u540d\\u79f0id\",\"title_en\":\"\",\"x-decorator\":\"FormItem\",\"x-component\":\"Input\",\"name\":\"id\",\"x-designable-id\":\"vj3uc5o2bis\",\"x-index\":5,\"type\":\"string\",\"hidden\":0,\"disabled\":0,\"required\":0,\"writeback\":1,\"placeholder\":\"\",\"length\":255},\"vi\":{\"title\":\"\\u793c\\u5305\\u540d\\u79f0vi\",\"title_en\":\"\",\"x-decorator\":\"FormItem\",\"x-component\":\"Input\",\"name\":\"vi\",\"x-designable-id\":\"w5fgy9x824c\",\"x-index\":6,\"type\":\"string\",\"hidden\":0,\"disabled\":0,\"required\":0,\"writeback\":1,\"placeholder\":\"\",\"length\":255},\"hi\":{\"title\":\"\\u793c\\u5305\\u540d\\u79f0hi\",\"title_en\":\"\",\"x-decorator\":\"FormItem\",\"x-component\":\"Input\",\"name\":\"hi\",\"x-designable-id\":\"4gysmw58fo3\",\"x-index\":7,\"type\":\"string\",\"hidden\":0,\"disabled\":0,\"required\":0,\"writeback\":1,\"placeholder\":\"\",\"length\":255},\"bn\":{\"title\":\"\\u793c\\u5305\\u540d\\u79f0bn\",\"title_en\":\"\",\"x-decorator\":\"FormItem\",\"x-component\":\"Input\",\"name\":\"bn\",\"x-designable-id\":\"kmi8a3nl4s0\",\"x-index\":8,\"type\":\"string\",\"hidden\":0,\"disabled\":0,\"required\":0,\"writeback\":1,\"placeholder\":\"\",\"length\":255},\"ur\":{\"title\":\"\\u793c\\u5305\\u540d\\u79f0ur\",\"title_en\":\"\",\"x-decorator\":\"FormItem\",\"x-component\":\"Input\",\"name\":\"ur\",\"x-designable-id\":\"vtrdguijp8c\",\"x-index\":9,\"type\":\"string\",\"hidden\":0,\"disabled\":0,\"required\":0,\"writeback\":1,\"placeholder\":\"\",\"length\":255},\"tl\":{\"title\":\"\\u793c\\u5305\\u540d\\u79f0tl\",\"title_en\":\"\",\"x-decorator\":\"FormItem\",\"x-component\":\"Input\",\"name\":\"tl\",\"x-designable-id\":\"56tubs428qe\",\"x-index\":10,\"type\":\"string\",\"hidden\":0,\"disabled\":0,\"required\":0,\"writeback\":1,\"placeholder\":\"\",\"length\":255},\"remark\":{\"title\":\"\\u793c\\u5305\\u540e\\u53f0\\u5907\\u6ce8\",\"title_en\":\"\",\"x-decorator\":\"FormItem\",\"x-component\":\"Input.TextArea\",\"name\":\"remark\",\"x-designable-id\":\"8x6j9s0zvtk\",\"x-index\":11,\"type\":\"string\",\"hidden\":0,\"disabled\":0,\"required\":0,\"writeback\":1,\"placeholder\":\"\",\"length\":255}}},\"1l26qivwn34\":{\"type\":\"void\",\"x-component\":\"Card\",\"x-component-props\":{\"title\":\"\\u5931\\u6548\",\"action\":\"operate\",\"position\":\"operateArea\",\"drive\":\"mysql\",\"btnForm\":\"text\",\"btnContent\":\"\\u5931\\u6548\",\"width\":640,\"show\":\"record.status!=1\",\"url\":\"\\\/operate\\\/welcomegiftbag\\\/unvalid\"},\"cardType\":\"modal\",\"x-designable-id\":\"1l26qivwn34\",\"x-index\":4,\"width\":640,\"properties\":{\"bid\":{\"title\":\"id\",\"title_en\":\"\",\"x-decorator\":\"FormItem\",\"x-component\":\"Input\",\"name\":\"bid\",\"x-designable-id\":\"htasxpg9vrq\",\"x-index\":0,\"type\":\"string\",\"hidden\":1,\"disabled\":0,\"required\":1,\"writeback\":1,\"placeholder\":\"\",\"length\":255},\"tips\":{\"title\":\"tips\",\"title_en\":\"\",\"x-decorator\":\"FormItem\",\"x-component\":\"MyText\",\"name\":\"tips\",\"x-designable-id\":\"1b9afvjkn3o\",\"x-index\":1,\"type\":\"string\",\"hidden\":0,\"disabled\":0,\"required\":0,\"writeback\":0,\"placeholder\":\"\",\"content\":\"\\u662f\\u5426\\u7f6e\\u6210\\u5931\\u6548\\uff0c\\u82e5\\u7f6e\\u6210\\u5931\\u6548\\uff0c\\u5df2\\u53d1\\u7ed9\\u9080\\u8bf7\\u4eba\\u7684\\u793c\\u5305\\u5c06\\u5168\\u90e8\\u5931\\u6548\",\"length\":255}}}},\"x-designable-id\":\"fqpkilzwedd\"}}","guid":"welcomegiftbag","model":"\\Imee\\Models\\Xs\\XsGiftBag","table_config":"{\"fields\":{\"bid\":{\"type\":\"varchar\",\"length\":255,\"default\":null,\"component\":\"input\",\"comment\":\"礼包id\",\"comment_en\":\"\"},\"cn\":{\"type\":\"varchar\",\"length\":255,\"default\":null,\"component\":\"input\",\"comment\":\"礼包名称cn\",\"comment_en\":\"\"},\"en\":{\"type\":\"varchar\",\"length\":255,\"default\":null,\"component\":\"input\",\"comment\":\"礼包名称en\",\"comment_en\":\"\"},\"ar\":{\"type\":\"varchar\",\"length\":255,\"default\":null,\"component\":\"input\",\"comment\":\"礼包名称ar\",\"comment_en\":\"\"},\"reward_str\":{\"type\":\"varchar\",\"length\":255,\"default\":null,\"component\":\"input\",\"comment\":\"礼包物品\",\"comment_en\":\"\"},\"remark\":{\"type\":\"varchar\",\"length\":255,\"default\":null,\"component\":\"input\",\"comment\":\"礼包后台备注\",\"comment_en\":\"\"},\"display_status\":{\"type\":\"varchar\",\"length\":255,\"default\":null,\"component\":\"input\",\"comment\":\"状态\",\"comment_en\":\"\"},\"name\":{\"type\":\"varchar\",\"length\":255,\"default\":null,\"component\":\"input\",\"comment\":\"礼包名称\",\"comment_en\":\"\"},\"status\":{\"type\":\"varchar\",\"length\":255,\"default\":null,\"component\":\"select\",\"comment\":\"状态 \",\"comment_en\":\"\"},\"ms\":{\"type\":\"varchar\",\"length\":255,\"default\":null,\"component\":\"input\",\"comment\":\"礼包名称ms\",\"comment_en\":\"\"},\"id\":{\"type\":\"varchar\",\"length\":255,\"default\":null,\"component\":\"input\",\"comment\":\"礼包名称id\",\"comment_en\":\"\"},\"vi\":{\"type\":\"varchar\",\"length\":255,\"default\":null,\"component\":\"input\",\"comment\":\"礼包名称vi\",\"comment_en\":\"\"},\"hi\":{\"type\":\"varchar\",\"length\":255,\"default\":null,\"component\":\"input\",\"comment\":\"礼包名称hi\",\"comment_en\":\"\"},\"bn\":{\"type\":\"varchar\",\"length\":255,\"default\":null,\"component\":\"input\",\"comment\":\"礼包名称bn\",\"comment_en\":\"\"},\"ur\":{\"type\":\"varchar\",\"length\":255,\"default\":null,\"component\":\"input\",\"comment\":\"礼包名称ur\",\"comment_en\":\"\"},\"tl\":{\"type\":\"varchar\",\"length\":255,\"default\":null,\"component\":\"input\",\"comment\":\"礼包名称tl\",\"comment_en\":\"\"},\"tips\":{\"type\":\"varchar\",\"length\":255,\"default\":null,\"component\":\"text\",\"comment\":\"tips\",\"comment_en\":\"\"}},\"pk\":\"bid\",\"visible\":[],\"disable\":[],\"data\":[],\"value\":[],\"comment\":\"礼包配置\",\"comment_en\":\"\"}","system_id":4}],"Imee\\Models\\Cms\\Lesscode\\LesscodeSchemaPoint":[{"id":21415,"guid":"welcomegiftbag","title":"列表","type":"list","drive":"mysql","state":1,"is_system":0,"logic":"","create_time":1745827419,"update_time":0,"system_id":4},{"id":21416,"guid":"welcomegiftbag","title":"添加礼包","type":"action","drive":"mysql","state":1,"is_system":0,"logic":"","create_time":1745827419,"update_time":0,"system_id":4},{"id":21417,"guid":"welcomegiftbag","title":"编辑","type":"modify","drive":"mysql","state":1,"is_system":0,"logic":"","create_time":1745827420,"update_time":0,"system_id":4},{"id":21418,"guid":"welcomegiftbag","title":"失效","type":"modal","drive":"mysql","state":1,"is_system":0,"logic":"","create_time":1745827420,"update_time":0,"system_id":4}],"Imee\\Models\\Cms\\Lesscode\\LesscodeSchemaPointConfig":[{"id":21415,"guid":"welcomegiftbag","point_id":21415,"config":"{\"list\":{\"bid\":{\"component\":\"input\",\"hidden\":0,\"required\":0,\"disabled\":0,\"comment\":\"\\u793c\\u5305id\",\"commentEn\":\"\",\"placeholder\":\"\"},\"cn\":{\"component\":\"input\",\"hidden\":0,\"required\":0,\"disabled\":0,\"comment\":\"\\u793c\\u5305\\u540d\\u79f0cn\",\"commentEn\":\"\",\"placeholder\":\"\"},\"en\":{\"component\":\"input\",\"hidden\":0,\"required\":0,\"disabled\":0,\"comment\":\"\\u793c\\u5305\\u540d\\u79f0en\",\"commentEn\":\"\",\"placeholder\":\"\"},\"ar\":{\"component\":\"input\",\"hidden\":0,\"required\":0,\"disabled\":0,\"comment\":\"\\u793c\\u5305\\u540d\\u79f0ar\",\"commentEn\":\"\",\"placeholder\":\"\"},\"reward_str\":{\"component\":\"input\",\"hidden\":0,\"required\":0,\"disabled\":0,\"comment\":\"\\u793c\\u5305\\u7269\\u54c1\",\"commentEn\":\"\",\"placeholder\":\"\",\"isHtml\":1},\"remark\":{\"component\":\"input\",\"hidden\":0,\"required\":0,\"disabled\":0,\"comment\":\"\\u793c\\u5305\\u540e\\u53f0\\u5907\\u6ce8\",\"commentEn\":\"\",\"placeholder\":\"\"},\"display_status\":{\"component\":\"input\",\"hidden\":0,\"required\":0,\"disabled\":0,\"comment\":\"\\u72b6\\u6001\",\"commentEn\":\"\",\"placeholder\":\"\"}},\"filter\":{\"bid\":{\"component\":\"input\",\"placeholder\":\"\",\"comment\":\"\\u793c\\u5305id\"},\"name\":{\"component\":\"input\",\"placeholder\":\"\",\"comment\":\"\\u793c\\u5305\\u540d\\u79f0\"},\"status\":{\"component\":\"select\",\"enum\":[],\"func\":{\"service\":\"\\\\Imee\\\\Service\\\\Operate\\\\WelcomegiftbagService\",\"method\":\"getStatus\",\"params\":[null,\"label,value\"]},\"placeholder\":\"\",\"comment\":\"\\u72b6\\u6001 \"}}}","create_time":1745827419,"update_time":0,"system_id":4},{"id":21416,"guid":"welcomegiftbag","point_id":21416,"config":"{\"params\":[[\"url\",\"\\\/operate\\\/welcomegiftbag\\\/create\"]],\"type\":\"manMadeModal\",\"modal_id\":\"add_gift_bag\",\"url\":\"\\\/operate\\\/welcomegiftbag\\\/create\",\"modalTitle\":\"\\u6dfb\\u52a0\\u793c\\u5305\",\"modalTitleEn\":\"\",\"title\":\"\\u6dfb\\u52a0\\u793c\\u5305\",\"title_en\":\"\"}","create_time":1745827420,"update_time":0,"system_id":4},{"id":21417,"guid":"welcomegiftbag","point_id":21417,"config":"{\"type\":\"modal\",\"fields\":{\"bid\":{\"component\":\"input\",\"hidden\":1,\"required\":1,\"disabled\":0,\"writeback\":1,\"comment\":\"id\",\"commentEn\":\"\",\"placeholder\":\"\"},\"cn\":{\"component\":\"input\",\"hidden\":0,\"required\":1,\"disabled\":0,\"writeback\":1,\"comment\":\"\\u793c\\u5305\\u540d\\u79f0cn\",\"commentEn\":\"\",\"placeholder\":\"\"},\"en\":{\"component\":\"input\",\"hidden\":0,\"required\":1,\"disabled\":0,\"writeback\":1,\"comment\":\"\\u793c\\u5305\\u540d\\u79f0en\",\"commentEn\":\"\",\"placeholder\":\"\"},\"ar\":{\"component\":\"input\",\"hidden\":0,\"required\":0,\"disabled\":0,\"writeback\":1,\"comment\":\"\\u793c\\u5305\\u540d\\u79f0ar\",\"commentEn\":\"\",\"placeholder\":\"\"},\"ms\":{\"component\":\"input\",\"hidden\":0,\"required\":0,\"disabled\":0,\"writeback\":1,\"comment\":\"\\u793c\\u5305\\u540d\\u79f0ms\",\"commentEn\":\"\",\"placeholder\":\"\"},\"id\":{\"component\":\"input\",\"hidden\":0,\"required\":0,\"disabled\":0,\"writeback\":1,\"comment\":\"\\u793c\\u5305\\u540d\\u79f0id\",\"commentEn\":\"\",\"placeholder\":\"\"},\"vi\":{\"component\":\"input\",\"hidden\":0,\"required\":0,\"disabled\":0,\"writeback\":1,\"comment\":\"\\u793c\\u5305\\u540d\\u79f0vi\",\"commentEn\":\"\",\"placeholder\":\"\"},\"hi\":{\"component\":\"input\",\"hidden\":0,\"required\":0,\"disabled\":0,\"writeback\":1,\"comment\":\"\\u793c\\u5305\\u540d\\u79f0hi\",\"commentEn\":\"\",\"placeholder\":\"\"},\"bn\":{\"component\":\"input\",\"hidden\":0,\"required\":0,\"disabled\":0,\"writeback\":1,\"comment\":\"\\u793c\\u5305\\u540d\\u79f0bn\",\"commentEn\":\"\",\"placeholder\":\"\"},\"ur\":{\"component\":\"input\",\"hidden\":0,\"required\":0,\"disabled\":0,\"writeback\":1,\"comment\":\"\\u793c\\u5305\\u540d\\u79f0ur\",\"commentEn\":\"\",\"placeholder\":\"\"},\"tl\":{\"component\":\"input\",\"hidden\":0,\"required\":0,\"disabled\":0,\"writeback\":1,\"comment\":\"\\u793c\\u5305\\u540d\\u79f0tl\",\"commentEn\":\"\",\"placeholder\":\"\"},\"remark\":{\"component\":\"input.textarea\",\"hidden\":0,\"required\":0,\"disabled\":0,\"writeback\":1,\"comment\":\"\\u793c\\u5305\\u540e\\u53f0\\u5907\\u6ce8\",\"commentEn\":\"\",\"placeholder\":\"\"}},\"url\":\"\\\/operate\\\/welcomegiftbag\\\/modify\",\"show\":\"record.status == 0\",\"width\":640,\"modalTitle\":\"\\u7f16\\u8f91\",\"modalTitleEn\":\"\",\"title\":\"\\u7f16\\u8f91\",\"title_en\":\"\",\"onlyText\":true}","create_time":1745827420,"update_time":0,"system_id":4},{"id":21418,"guid":"welcomegiftbag","point_id":21418,"config":"{\"type\":\"modal\",\"fields\":{\"bid\":{\"component\":\"input\",\"hidden\":1,\"required\":1,\"disabled\":0,\"writeback\":1,\"comment\":\"id\",\"commentEn\":\"\",\"placeholder\":\"\"},\"tips\":{\"content\":\"\\u662f\\u5426\\u7f6e\\u6210\\u5931\\u6548\\uff0c\\u82e5\\u7f6e\\u6210\\u5931\\u6548\\uff0c\\u5df2\\u53d1\\u7ed9\\u9080\\u8bf7\\u4eba\\u7684\\u793c\\u5305\\u5c06\\u5168\\u90e8\\u5931\\u6548\",\"component\":\"text\",\"hidden\":0,\"required\":0,\"disabled\":0,\"writeback\":0,\"comment\":\"tips\",\"commentEn\":\"\",\"placeholder\":\"\"}},\"url\":\"\\\/operate\\\/welcomegiftbag\\\/unvalid\",\"show\":\"record.status!=1\",\"width\":640,\"modalTitle\":\"\\u5931\\u6548\",\"modalTitleEn\":\"\",\"title\":\"\\u5931\\u6548\",\"title_en\":\"\",\"onlyText\":true}","create_time":1745827420,"update_time":0,"system_id":4}]}