{"Imee\\Models\\Cms\\Lesscode\\LesscodeSchemaConfig":[{"id":103,"schema_json":"{\"form\":{\"labelCol\":6,\"wrapperCol\":12,\"name\":\"\\u81ea\\u5b9a\\u4e49\\u80cc\\u666f\\u7ba1\\u7406\",\"filterCache\":0},\"schema\":{\"type\":\"object\",\"properties\":{\"v4rai5e1y7u\":{\"type\":\"void\",\"x-component\":\"Card\",\"x-component-props\":{\"title\":\"\\u5217\\u8868\",\"action\":\"list\",\"drive\":\"mysql\",\"pk\":\"bg_id\"},\"cardType\":\"list\",\"x-designable-id\":\"v4rai5e1y7u\",\"x-index\":0,\"properties\":{\"sn\":{\"title\":\"SN\",\"x-decorator\":\"FormItem\",\"x-component\":\"NumberPicker\",\"name\":\"sn\",\"x-designable-id\":\"2wuajcp0x4y\",\"x-index\":0,\"type\":\"number\",\"hidden\":0,\"disabled\":0,\"required\":0,\"placeholder\":\"\",\"length\":10},\"bg_id\":{\"title\":\"Background ID\",\"x-decorator\":\"FormItem\",\"x-component\":\"NumberPicker\",\"name\":\"bg_id\",\"x-designable-id\":\"4jrhq2wgfb6\",\"x-index\":1,\"type\":\"number\",\"hidden\":0,\"disabled\":0,\"required\":0,\"placeholder\":\"\",\"length\":10},\"mid\":{\"title\":\"Material ID\",\"x-decorator\":\"FormItem\",\"x-component\":\"NumberPicker\",\"name\":\"mid\",\"x-designable-id\":\"k128h4te9vf\",\"x-index\":2,\"type\":\"number\",\"hidden\":0,\"disabled\":0,\"required\":0,\"placeholder\":\"\",\"length\":10},\"cover\":{\"title\":\"Region Cover\",\"x-decorator\":\"FormItem\",\"x-component\":\"Input\",\"name\":\"cover\",\"x-designable-id\":\"nesj3806mwp\",\"x-index\":3,\"type\":\"string\",\"hidden\":0,\"disabled\":0,\"required\":0,\"placeholder\":\"\",\"dataType\":\"img\",\"length\":255},\"duration\":{\"title\":\"Duration\",\"x-decorator\":\"FormItem\",\"x-component\":\"Input\",\"name\":\"duration\",\"x-designable-id\":\"fjkr03xwn8b\",\"x-index\":4,\"type\":\"string\",\"hidden\":0,\"disabled\":0,\"required\":0,\"placeholder\":\"\",\"length\":255},\"price\":{\"title\":\"Price\",\"x-decorator\":\"FormItem\",\"x-component\":\"NumberPicker\",\"name\":\"price\",\"x-designable-id\":\"1438ivbp2xj\",\"x-index\":5,\"type\":\"number\",\"hidden\":0,\"disabled\":0,\"required\":0,\"placeholder\":\"\",\"length\":10},\"is_free\":{\"title\":\"Free\",\"x-decorator\":\"FormItem\",\"x-component\":\"Select\",\"name\":\"is_free\",\"x-designable-id\":\"cwlhb1e4vyu\",\"x-index\":6,\"type\":\"\",\"hidden\":0,\"disabled\":0,\"required\":0,\"placeholder\":\"\",\"length\":1,\"enum\":[{\"children\":[],\"label\":\"YES\",\"value\":\"1\"},{\"children\":[],\"label\":\"NO\",\"value\":\"0\"}]},\"name\":{\"title\":\"Background Name\",\"x-decorator\":\"FormItem\",\"x-component\":\"Input\",\"name\":\"name\",\"x-designable-id\":\"069phd4g1jv\",\"x-index\":7,\"type\":\"string\",\"hidden\":0,\"disabled\":0,\"required\":0,\"placeholder\":\"\",\"style\":\"{\\\"width\\\":150}\",\"length\":255},\"big_area\":{\"title\":\"Region\",\"x-decorator\":\"FormItem\",\"x-component\":\"Input\",\"name\":\"big_area\",\"x-designable-id\":\"ju7std8hgel\",\"x-index\":8,\"type\":\"string\",\"hidden\":0,\"disabled\":0,\"required\":0,\"placeholder\":\"\",\"length\":255},\"state\":{\"title\":\"Shelf Status\",\"x-decorator\":\"FormItem\",\"x-component\":\"Select\",\"name\":\"state\",\"x-designable-id\":\"gm0ywdl3er4\",\"x-index\":9,\"type\":\"\",\"hidden\":0,\"disabled\":0,\"required\":0,\"placeholder\":\"\",\"length\":1,\"enum\":[{\"children\":[],\"label\":\"OFF\",\"value\":\"0\"},{\"children\":[],\"label\":\"ON\",\"value\":\"1\"}]},\"effective_time\":{\"title\":\"Effective Time\",\"x-decorator\":\"FormItem\",\"x-component\":\"DatePicker\",\"name\":\"effective_time\",\"x-designable-id\":\"yjxalse63r7\",\"x-index\":10,\"type\":\"string\",\"hidden\":0,\"disabled\":0,\"required\":0,\"placeholder\":\"\",\"flag\":\"year_time\",\"single\":1,\"length\":10},\"source\":{\"title\":\"Source\",\"x-decorator\":\"FormItem\",\"x-component\":\"Select\",\"name\":\"source\",\"x-designable-id\":\"0kgr4byf5p7\",\"x-index\":11,\"type\":\"\",\"hidden\":0,\"disabled\":0,\"required\":0,\"placeholder\":\"\",\"length\":1,\"enum\":[{\"children\":[],\"label\":\"\\u7ba1\\u7406\\u540e\\u53f0\",\"value\":\"0\"},{\"children\":[],\"label\":\"\\u7528\\u6237\\u5b9a\\u5236\",\"value\":\"1\"}]}}},\"xh4nq7ypzvk\":{\"type\":\"void\",\"x-component\":\"Card\",\"x-component-props\":{\"title\":\"\\u7b5b\\u9009\",\"action\":\"filter\"},\"cardType\":\"filter\",\"x-designable-id\":\"xh4nq7ypzvk\",\"x-index\":1,\"properties\":{\"bg_id\":{\"title\":\"Background ID\",\"x-decorator\":\"FormItem\",\"x-component\":\"Input\",\"name\":\"bg_id\",\"x-designable-id\":\"7lw8yig02bk\",\"x-index\":0,\"type\":\"string\",\"hidden\":0,\"disabled\":0,\"required\":0,\"placeholder\":\"\",\"length\":10},\"mid\":{\"title\":\"Material ID\",\"x-decorator\":\"FormItem\",\"x-component\":\"Input\",\"name\":\"mid\",\"x-designable-id\":\"yp7kg1et8jc\",\"x-index\":1,\"type\":\"string\",\"hidden\":0,\"disabled\":0,\"required\":0,\"placeholder\":\"\",\"length\":10},\"big_area\":{\"title\":\"Region\",\"x-decorator\":\"FormItem\",\"x-component\":\"Select\",\"name\":\"big_area\",\"x-designable-id\":\"62qgd79a0cj\",\"x-index\":2,\"type\":\"\",\"hidden\":0,\"disabled\":0,\"required\":0,\"placeholder\":\"\",\"length\":255,\"service\":\"\\\\Imee\\\\Service\\\\StatusService\",\"method\":\"getBigAreaCode\",\"params\":\"{\\\"params\\\":[null,\\\"label,value\\\"]}\"},\"state\":{\"title\":\"Shelf Status\",\"x-decorator\":\"FormItem\",\"x-component\":\"Select\",\"name\":\"state\",\"x-designable-id\":\"da2wz7lvuge\",\"x-index\":3,\"type\":\"\",\"hidden\":0,\"disabled\":0,\"required\":0,\"placeholder\":\"\",\"length\":1,\"enum\":[{\"children\":[],\"label\":\"OFF\",\"value\":\"0\"},{\"children\":[],\"label\":\"ON\",\"value\":\"1\"}]}}},\"t1izunbcp8a\":{\"type\":\"void\",\"x-component\":\"Card\",\"x-component-props\":{\"title\":\"Add\",\"action\":\"action\",\"position\":\"createArea\",\"drive\":\"mysql\",\"btnForm\":\"text\",\"btnContent\":\"Add\",\"width\":640,\"url\":\"\\\/operate\\\/custombackground\\\/create\"},\"cardType\":\"modal\",\"x-designable-id\":\"t1izunbcp8a\",\"x-index\":2,\"width\":640,\"properties\":{\"big_area\":{\"title\":\"Region\",\"x-decorator\":\"FormItem\",\"x-component\":\"Select\",\"name\":\"big_area\",\"x-designable-id\":\"elqd60hbuj5\",\"x-index\":0,\"type\":\"\",\"hidden\":0,\"disabled\":0,\"required\":1,\"placeholder\":\"\",\"length\":255,\"service\":\"\\\\Imee\\\\Service\\\\StatusService\",\"method\":\"getBigAreaCode\",\"params\":\"{\\\"params\\\":[null,\\\"label,value\\\"]}\"},\"mid\":{\"title\":\"Material ID\",\"x-decorator\":\"FormItem\",\"x-component\":\"DynamicSelect\",\"name\":\"mid\",\"required\":1,\"url\":\"\\\/operate\\\/custombackground\\\/create?c=enum\",\"x-designable-id\":\"2ytdg6j3nzq\",\"x-index\":1},\"name\":{\"title\":\"Name\",\"x-decorator\":\"FormItem\",\"x-component\":\"Input\",\"name\":\"name\",\"x-designable-id\":\"le270jmzn4u\",\"x-index\":2,\"type\":\"string\",\"hidden\":0,\"disabled\":0,\"required\":1,\"placeholder\":\"\",\"style\":\"{\\\"width\\\":150}\",\"dataType\":\"img\",\"length\":255},\"sn\":{\"title\":\"SN\",\"x-decorator\":\"FormItem\",\"x-component\":\"NumberPicker\",\"name\":\"sn\",\"x-designable-id\":\"r7ej1s2gv8q\",\"x-index\":3,\"type\":\"number\",\"hidden\":0,\"disabled\":0,\"required\":1,\"placeholder\":\"\",\"length\":10},\"duration\":{\"title\":\"Duration(Day)\",\"x-decorator\":\"FormItem\",\"x-component\":\"NumberPicker\",\"name\":\"duration\",\"x-designable-id\":\"v4y8w9us1g0\",\"x-index\":4,\"type\":\"number\",\"hidden\":0,\"disabled\":0,\"required\":1,\"placeholder\":\"\",\"length\":255},\"cover\":{\"title\":\"Region Cover\",\"x-decorator\":\"FormItem\",\"x-component\":\"Upload\",\"name\":\"cover\",\"x-designable-id\":\"db9nxkh8e3y\",\"x-index\":5,\"type\":\"Array<object>\",\"hidden\":0,\"disabled\":0,\"required\":0,\"placeholder\":\"\",\"dataType\":\"img\",\"length\":255,\"x-component-props\":{\"textContent\":\"Upload\"}},\"state\":{\"title\":\"Shelf Status\",\"x-decorator\":\"FormItem\",\"x-component\":\"Select\",\"name\":\"state\",\"x-designable-id\":\"x0i6nj57cou\",\"x-index\":6,\"type\":\"\",\"hidden\":0,\"disabled\":0,\"required\":1,\"placeholder\":\"\",\"length\":1,\"enum\":[{\"children\":[],\"label\":\"OFF\",\"value\":\"0\"},{\"children\":[],\"label\":\"ON\",\"value\":\"1\"}]},\"effective_time\":{\"title\":\"Effective Time\",\"x-decorator\":\"FormItem\",\"x-component\":\"DatePicker\",\"name\":\"effective_time\",\"x-designable-id\":\"9oguctpsi73\",\"x-index\":7,\"type\":\"string\",\"hidden\":0,\"disabled\":0,\"required\":0,\"placeholder\":\"\",\"flag\":\"year_time\",\"single\":1,\"length\":10}}},\"ozgh9vkt1bf\":{\"type\":\"void\",\"x-component\":\"Card\",\"x-component-props\":{\"title\":\"Delete\",\"action\":\"operate\",\"position\":\"operateArea\",\"drive\":\"mysql\",\"btnForm\":\"text\",\"btnContent\":\"Delete\",\"show\":\"record.state == '0'\"},\"cardType\":\"delete\",\"x-designable-id\":\"ozgh9vkt1bf\",\"x-index\":3},\"9mrv8u0z3la\":{\"type\":\"void\",\"x-component\":\"Card\",\"x-component-props\":{\"title\":\"\\u64cd\\u4f5c\\u65e5\\u5fd7\",\"action\":\"operate\",\"position\":\"operateArea\",\"drive\":\"mysql\",\"btnForm\":\"text\",\"btnContent\":\"\\u64cd\\u4f5c\\u65e5\\u5fd7\",\"guid\":\"backgroundlog\"},\"cardType\":\"guid\",\"x-designable-id\":\"9mrv8u0z3la\",\"x-index\":4}},\"x-designable-id\":\"0g54uwuf7na\"}}","guid":"custombackground","model":"","table_config":"{\"fields\":{\"sn\":{\"type\":\"int\",\"length\":10,\"default\":null,\"component\":\"numberpicker\",\"comment\":\"SN\"},\"bg_id\":{\"type\":\"int\",\"length\":10,\"default\":null,\"component\":\"numberpicker\",\"comment\":\"Background ID\"},\"mid\":{\"type\":\"int\",\"length\":10,\"default\":null,\"component\":\"numberpicker\",\"comment\":\"Material ID\"},\"cover\":{\"type\":\"varchar\",\"length\":255,\"default\":null,\"component\":\"input\",\"comment\":\"Region Cover\"},\"duration\":{\"type\":\"varchar\",\"length\":255,\"default\":null,\"component\":\"input\",\"comment\":\"Duration\"},\"price\":{\"type\":\"int\",\"length\":10,\"default\":null,\"component\":\"numberpicker\",\"comment\":\"Price\"},\"is_free\":{\"type\":\"tinyint\",\"length\":1,\"default\":null,\"component\":\"select\",\"comment\":\"Free\"},\"name\":{\"type\":\"varchar\",\"length\":255,\"default\":null,\"component\":\"input\",\"comment\":\"Background Name\"},\"big_area\":{\"type\":\"varchar\",\"length\":255,\"default\":null,\"component\":\"input\",\"comment\":\"Region\"},\"state\":{\"type\":\"tinyint\",\"length\":1,\"default\":null,\"component\":\"select\",\"comment\":\"Shelf Status\"},\"effective_time\":{\"type\":\"int\",\"length\":10,\"default\":null,\"component\":\"datepicker\",\"comment\":\"Effective Time\"},\"source\":{\"type\":\"tinyint\",\"length\":1,\"default\":null,\"component\":\"select\",\"comment\":\"Source\"}},\"pk\":\"bg_id\",\"visible\":[],\"disable\":[],\"data\":[],\"value\":[],\"comment\":\"自定义背景管理\"}","system_id":4}],"Imee\\Models\\Cms\\Lesscode\\LesscodeSchemaPoint":[{"id":15423,"guid":"custombackground","title":"列表","type":"list","drive":"mysql","state":1,"is_system":0,"logic":"","create_time":1729845672,"update_time":0,"system_id":4},{"id":15424,"guid":"custombackground","title":"Add","type":"create","drive":"mysql","state":1,"is_system":0,"logic":"","create_time":1729845672,"update_time":0,"system_id":4},{"id":15425,"guid":"custombackground","title":"Delete","type":"delete","drive":"mysql","state":1,"is_system":0,"logic":"","create_time":1729845672,"update_time":0,"system_id":4},{"id":15426,"guid":"custombackground","title":"操作日志","type":"modal","drive":"mysql","state":1,"is_system":0,"logic":"","create_time":1729845672,"update_time":0,"system_id":4}],"Imee\\Models\\Cms\\Lesscode\\LesscodeSchemaPointConfig":[{"id":15423,"guid":"custombackground","point_id":15423,"config":"{\"list\":{\"sn\":{\"component\":\"numberpicker\",\"hidden\":0,\"required\":0,\"disabled\":0,\"comment\":\"SN\",\"placeholder\":\"\"},\"bg_id\":{\"component\":\"numberpicker\",\"hidden\":0,\"required\":0,\"disabled\":0,\"comment\":\"Background ID\",\"placeholder\":\"\"},\"mid\":{\"component\":\"numberpicker\",\"hidden\":0,\"required\":0,\"disabled\":0,\"comment\":\"Material ID\",\"placeholder\":\"\"},\"cover\":{\"component\":\"input\",\"hidden\":0,\"required\":0,\"disabled\":0,\"dataType\":\"img\",\"comment\":\"Region Cover\",\"placeholder\":\"\"},\"duration\":{\"component\":\"input\",\"hidden\":0,\"required\":0,\"disabled\":0,\"comment\":\"Duration\",\"placeholder\":\"\"},\"price\":{\"component\":\"numberpicker\",\"hidden\":0,\"required\":0,\"disabled\":0,\"comment\":\"Price\",\"placeholder\":\"\"},\"is_free\":{\"component\":\"select\",\"hidden\":0,\"required\":0,\"disabled\":0,\"enum\":[[\"YES\",\"1\"],[\"NO\",\"0\"]],\"func\":[],\"comment\":\"Free\",\"placeholder\":\"\"},\"name\":{\"component\":\"input\",\"hidden\":0,\"required\":0,\"disabled\":0,\"style\":{\"width\":150},\"comment\":\"Background Name\",\"placeholder\":\"\"},\"big_area\":{\"component\":\"input\",\"hidden\":0,\"required\":0,\"disabled\":0,\"comment\":\"Region\",\"placeholder\":\"\"},\"state\":{\"component\":\"select\",\"hidden\":0,\"required\":0,\"disabled\":0,\"enum\":[[\"OFF\",\"0\"],[\"ON\",\"1\"]],\"func\":[],\"comment\":\"Shelf Status\",\"placeholder\":\"\"},\"effective_time\":{\"component\":\"datepicker\",\"hidden\":0,\"required\":0,\"disabled\":0,\"flag\":\"year_time\",\"single\":true,\"comment\":\"Effective Time\",\"placeholder\":\"\",\"dateFormat\":\"Y-m-d H:i:s\"},\"source\":{\"component\":\"select\",\"hidden\":0,\"required\":0,\"disabled\":0,\"enum\":[[\"\\u7ba1\\u7406\\u540e\\u53f0\",\"0\"],[\"\\u7528\\u6237\\u5b9a\\u5236\",\"1\"]],\"func\":[],\"comment\":\"Source\",\"placeholder\":\"\"}},\"filter\":{\"bg_id\":{\"component\":\"input\",\"placeholder\":\"\",\"comment\":\"Background ID\"},\"mid\":{\"component\":\"input\",\"placeholder\":\"\",\"comment\":\"Material ID\"},\"big_area\":{\"component\":\"select\",\"enum\":[],\"func\":{\"service\":\"\\\\Imee\\\\Service\\\\StatusService\",\"method\":\"getBigAreaCode\",\"params\":[null,\"label,value\"]},\"placeholder\":\"\",\"comment\":\"Region\"},\"state\":{\"component\":\"select\",\"enum\":[[\"OFF\",\"0\"],[\"ON\",\"1\"]],\"func\":[],\"placeholder\":\"\",\"comment\":\"Shelf Status\"}}}","create_time":1729845672,"update_time":0,"system_id":4},{"id":15424,"guid":"custombackground","point_id":15424,"config":"{\"type\":\"modal\",\"fields\":{\"big_area\":{\"component\":\"select\",\"hidden\":0,\"required\":1,\"disabled\":0,\"enum\":[],\"func\":{\"service\":\"\\\\Imee\\\\Service\\\\StatusService\",\"method\":\"getBigAreaCode\",\"params\":[null,\"label,value\"]},\"comment\":\"Region\",\"placeholder\":\"\"},\"mid\":{\"component\":\"dynamicselect\",\"hidden\":false,\"required\":1,\"disabled\":false,\"enum\":[],\"func\":[],\"url\":\"\\\/operate\\\/custombackground\\\/create?c=enum\",\"comment\":\"Material ID\",\"placeholder\":\"\"},\"name\":{\"component\":\"input\",\"hidden\":0,\"required\":1,\"disabled\":0,\"dataType\":\"img\",\"style\":{\"width\":150},\"comment\":\"Name\",\"placeholder\":\"\"},\"sn\":{\"component\":\"numberpicker\",\"hidden\":0,\"required\":1,\"disabled\":0,\"comment\":\"SN\",\"placeholder\":\"\"},\"duration\":{\"component\":\"numberpicker\",\"hidden\":0,\"required\":1,\"disabled\":0,\"comment\":\"Duration(Day)\",\"placeholder\":\"\"},\"cover\":{\"component\":\"upload\",\"hidden\":0,\"required\":0,\"disabled\":0,\"comment\":\"Region Cover\",\"placeholder\":\"\"},\"state\":{\"component\":\"select\",\"hidden\":0,\"required\":1,\"disabled\":0,\"enum\":[[\"OFF\",\"0\"],[\"ON\",\"1\"]],\"func\":[],\"comment\":\"Shelf Status\",\"placeholder\":\"\"},\"effective_time\":{\"component\":\"datepicker\",\"hidden\":0,\"required\":0,\"disabled\":0,\"flag\":\"year_time\",\"single\":true,\"comment\":\"Effective Time\",\"placeholder\":\"\"}},\"url\":\"\\\/operate\\\/custombackground\\\/create\",\"width\":640,\"modalTitle\":\"Add\",\"title\":\"Add\"}","create_time":1729845672,"update_time":0,"system_id":4},{"id":15425,"guid":"custombackground","point_id":15425,"config":"{\"show\":\"record.state == '0'\",\"modalTitle\":\"Delete\",\"title\":\"Delete\",\"onlyText\":true}","create_time":1729845672,"update_time":0,"system_id":4},{"id":15426,"guid":"custombackground","point_id":15426,"config":"{\"type\":\"guid\",\"guid\":\"backgroundlog\",\"modalTitle\":\"\\u64cd\\u4f5c\\u65e5\\u5fd7\",\"title\":\"\\u64cd\\u4f5c\\u65e5\\u5fd7\",\"onlyText\":true}","create_time":1729845672,"update_time":0,"system_id":4}]}