{"Imee\\Models\\Cms\\Lesscode\\LesscodeSchemaConfig":[{"id":101,"schema_json":"{\"form\":{\"labelCol\":6,\"wrapperCol\":12,\"name\":\"\\u81ea\\u5b9a\\u4e49\\u80cc\\u666f\\u5361\\u4e0b\\u53d1\",\"name_en\":\"\",\"filterCache\":0},\"schema\":{\"type\":\"object\",\"properties\":{\"5psbmc8vgoz\":{\"type\":\"void\",\"x-component\":\"Card\",\"x-component-props\":{\"title\":\"\\u5217\\u8868\",\"title_en\":\"list\",\"action\":\"list\",\"drive\":\"mysql\",\"pk\":\"id\"},\"cardType\":\"list\",\"x-designable-id\":\"5psbmc8vgoz\",\"x-index\":0,\"properties\":{\"id\":{\"title\":\"\\u5e8f\\u53f7\",\"title_en\":\"\",\"x-decorator\":\"FormItem\",\"x-component\":\"NumberPicker\",\"name\":\"id\",\"x-designable-id\":\"tz1os28uaeq\",\"x-index\":0,\"type\":\"number\",\"hidden\":0,\"disabled\":0,\"required\":0,\"placeholder\":\"\",\"length\":10},\"uid\":{\"title\":\"UID\",\"title_en\":\"\",\"x-decorator\":\"FormItem\",\"x-component\":\"Input\",\"name\":\"uid\",\"x-designable-id\":\"bnfhudzrla4\",\"x-index\":1,\"type\":\"string\",\"hidden\":0,\"disabled\":0,\"required\":0,\"placeholder\":\"\",\"length\":255},\"big_area_id\":{\"title\":\"\\u5927\\u533a\",\"title_en\":\"\",\"x-decorator\":\"FormItem\",\"x-component\":\"Select\",\"name\":\"big_area_id\",\"x-designable-id\":\"c9uzq7tlhd6\",\"x-index\":2,\"type\":\"\",\"hidden\":0,\"disabled\":0,\"required\":0,\"placeholder\":\"\",\"length\":255,\"service\":\"\\\\Imee\\\\Service\\\\StatusService\",\"method\":\"getFamilyBigArea\",\"params\":\"{\\\"params\\\":[null,\\\"label,value\\\"]}\"},\"num\":{\"title\":\"\\u80cc\\u666f\\u5361\\u6570\\u91cf\",\"title_en\":\"\",\"x-decorator\":\"FormItem\",\"x-component\":\"Input\",\"name\":\"num\",\"x-designable-id\":\"32xntibzp4g\",\"x-index\":3,\"type\":\"string\",\"hidden\":0,\"disabled\":0,\"required\":0,\"placeholder\":\"\",\"length\":255},\"card_type\":{\"title\":\"\\u7c7b\\u578b\",\"title_en\":\"\",\"x-decorator\":\"FormItem\",\"x-component\":\"Select\",\"name\":\"card_type\",\"x-designable-id\":\"s21aob9ekq4\",\"x-index\":4,\"type\":\"\",\"hidden\":0,\"disabled\":0,\"required\":0,\"placeholder\":\"\",\"length\":255,\"service\":\"Imee\\\\Service\\\\Operate\\\\Background\\\\Custombackground\\\\CustomBgcCardSendService\",\"method\":\"getCardTypeMap\",\"params\":\"{\\\"params\\\":[null,\\\"label,value\\\"]}\"},\"valid_term\":{\"title\":\"\\u5355\\u5f20\\u80cc\\u666f\\u5361\\u6709\\u6548\\u671f\\uff08\\u5929\\uff09\",\"title_en\":\"\",\"x-decorator\":\"FormItem\",\"x-component\":\"Input\",\"name\":\"valid_term\",\"x-designable-id\":\"961qb0fhrgd\",\"x-index\":5,\"type\":\"string\",\"hidden\":0,\"disabled\":0,\"required\":0,\"placeholder\":\"\",\"style\":\"{\\\"width\\\":200}\",\"length\":255},\"can_transfer\":{\"title\":\"\\u662f\\u5426\\u53ef\\u8d60\\u9001\",\"title_en\":\"\",\"x-decorator\":\"FormItem\",\"x-component\":\"Select\",\"name\":\"can_transfer\",\"x-designable-id\":\"p2z3tjwlhor\",\"x-index\":6,\"type\":\"\",\"hidden\":0,\"disabled\":0,\"required\":0,\"placeholder\":\"\",\"length\":1,\"enum\":[{\"children\":[],\"label\":\"\\u662f\",\"value\":\"1\"},{\"children\":[],\"label\":\"\\u5426\",\"value\":\"0\"}]},\"reason\":{\"title\":\"\\u53d1\\u653e\\u7406\\u7531\",\"title_en\":\"\",\"x-decorator\":\"FormItem\",\"x-component\":\"Input\",\"name\":\"reason\",\"x-designable-id\":\"apxz1il9ryu\",\"x-index\":7,\"type\":\"string\",\"hidden\":0,\"disabled\":0,\"required\":0,\"placeholder\":\"\",\"length\":255},\"operator\":{\"title\":\"\\u64cd\\u4f5c\\u4eba\",\"title_en\":\"\",\"x-decorator\":\"FormItem\",\"x-component\":\"Input\",\"name\":\"operator\",\"x-designable-id\":\"pszjcwi053r\",\"x-index\":8,\"type\":\"string\",\"hidden\":0,\"disabled\":0,\"required\":0,\"placeholder\":\"\",\"length\":255},\"dateline\":{\"title\":\"\\u64cd\\u4f5c\\u65f6\\u95f4\",\"title_en\":\"\",\"x-decorator\":\"FormItem\",\"x-component\":\"DatePicker\",\"name\":\"dateline\",\"x-designable-id\":\"zvm0fn3bij9\",\"x-index\":9,\"type\":\"string\",\"hidden\":0,\"disabled\":0,\"required\":0,\"placeholder\":\"\",\"single\":1,\"length\":10}}},\"4r6xpwy5fn0\":{\"type\":\"void\",\"x-component\":\"Card\",\"x-component-props\":{\"title\":\"\\u7b5b\\u9009\",\"title_en\":\"filter\",\"action\":\"filter\"},\"cardType\":\"filter\",\"x-designable-id\":\"4r6xpwy5fn0\",\"x-index\":1,\"properties\":{\"uid\":{\"title\":\"UID\",\"title_en\":\"\",\"x-decorator\":\"FormItem\",\"x-component\":\"Input\",\"name\":\"uid\",\"x-designable-id\":\"9nfob6wlqzj\",\"x-index\":0,\"type\":\"string\",\"hidden\":0,\"disabled\":0,\"required\":0,\"placeholder\":\"\",\"length\":255},\"big_area_id\":{\"title\":\"\\u5927\\u533a\",\"title_en\":\"\",\"x-decorator\":\"FormItem\",\"x-component\":\"Select\",\"name\":\"big_area_id\",\"x-designable-id\":\"6k19eclipoh\",\"x-index\":1,\"type\":\"\",\"hidden\":0,\"disabled\":0,\"required\":0,\"placeholder\":\"\",\"length\":255,\"service\":\"\\\\Imee\\\\Service\\\\StatusService\",\"method\":\"getFamilyBigArea\",\"params\":\"{\\\"params\\\":[null,\\\"label,value\\\"]}\"},\"dateline\":{\"title\":\"\\u64cd\\u4f5c\\u65f6\\u95f4\",\"title_en\":\"\",\"x-decorator\":\"FormItem\",\"x-component\":\"DatePicker.RangePicker\",\"name\":\"dateline\",\"x-designable-id\":\"qzxyrp6ej0o\",\"x-index\":2,\"type\":\"\",\"hidden\":0,\"disabled\":0,\"required\":0,\"placeholder\":\"\",\"flag\":\"date\",\"single\":0,\"length\":10},\"card_type\":{\"title\":\"\\u7c7b\\u578b\",\"title_en\":\"\",\"x-decorator\":\"FormItem\",\"x-component\":\"Select\",\"name\":\"card_type\",\"x-designable-id\":\"q8p8dxjaf3y\",\"x-index\":3,\"type\":\"\",\"hidden\":0,\"disabled\":0,\"required\":0,\"placeholder\":\"\",\"length\":255,\"service\":\"Imee\\\\Service\\\\Operate\\\\Background\\\\Custombackground\\\\CustomBgcCardSendService\",\"method\":\"getCardTypeMap\",\"params\":\"{\\\"params\\\":[null,\\\"label,value\\\"]}\"}}},\"bfqz708jek5\":{\"type\":\"void\",\"x-component\":\"Card\",\"x-component-props\":{\"title\":\"\\u53d1\\u653e\",\"action\":\"action\",\"position\":\"createArea\",\"drive\":\"mysql\",\"btnForm\":\"text\",\"btnContent\":\"\\u53d1\\u653e\",\"width\":640,\"url\":\"\\\/operate\\\/background\\\/custombgccardsend\\\/send\"},\"cardType\":\"modal\",\"x-designable-id\":\"bfqz708jek5\",\"x-index\":2,\"width\":640,\"properties\":{\"uid\":{\"title\":\"UID\",\"title_en\":\"\",\"x-decorator\":\"FormItem\",\"x-component\":\"Input\",\"name\":\"uid\",\"x-designable-id\":\"7xslkq0dcz1\",\"x-index\":0,\"type\":\"string\",\"hidden\":0,\"disabled\":0,\"required\":1,\"placeholder\":\"\",\"length\":255},\"num\":{\"title\":\"\\u6570\\u91cf\",\"title_en\":\"\",\"x-decorator\":\"FormItem\",\"x-component\":\"Input\",\"name\":\"num\",\"x-designable-id\":\"7423s6f9wio\",\"x-index\":1,\"type\":\"string\",\"hidden\":0,\"disabled\":0,\"required\":1,\"placeholder\":\"\",\"length\":255},\"card_type\":{\"title\":\"\\u7c7b\\u578b\",\"title_en\":\"\",\"x-decorator\":\"FormItem\",\"x-component\":\"Select\",\"name\":\"card_type\",\"x-designable-id\":\"ti1jypeg8q4\",\"x-index\":2,\"type\":\"\",\"hidden\":0,\"disabled\":0,\"required\":1,\"placeholder\":\"\",\"length\":255,\"service\":\"Imee\\\\Service\\\\Operate\\\\Background\\\\Custombackground\\\\CustomBgcCardSendService\",\"method\":\"getCardTypeMap\",\"params\":\"{\\\"params\\\":[null,\\\"label,value\\\"]}\"},\"valid_term\":{\"title\":\"\\u5355\\u5f20\\u6709\\u6548\\u671f\\uff08\\u5929\\uff09\",\"title_en\":\"\",\"x-decorator\":\"FormItem\",\"x-component\":\"Input\",\"name\":\"valid_term\",\"x-designable-id\":\"k9epia16t7g\",\"x-index\":3,\"type\":\"string\",\"hidden\":0,\"disabled\":0,\"required\":1,\"placeholder\":\"\",\"style\":\"{\\\"width\\\":200}\",\"length\":255},\"can_transfer\":{\"title\":\"\\u662f\\u5426\\u53ef\\u8d60\\u9001\",\"title_en\":\"\",\"x-decorator\":\"FormItem\",\"x-component\":\"Select\",\"name\":\"can_transfer\",\"x-designable-id\":\"lwxafh0vp5y\",\"x-index\":4,\"type\":\"\",\"hidden\":0,\"disabled\":0,\"required\":0,\"default\":\"1\",\"placeholder\":\"\",\"length\":1,\"enum\":[{\"children\":[],\"label\":\"\\u662f\",\"value\":\"1\"},{\"children\":[],\"label\":\"\\u5426\",\"value\":\"0\"}]},\"reason\":{\"title\":\"\\u53d1\\u653e\\u7406\\u7531\",\"title_en\":\"\",\"x-decorator\":\"FormItem\",\"x-component\":\"Input.TextArea\",\"name\":\"reason\",\"x-designable-id\":\"7thlxgd2myn\",\"x-index\":5,\"type\":\"string\",\"hidden\":0,\"disabled\":0,\"required\":1,\"placeholder\":\"\",\"length\":255}}},\"kz1j0vuqxsf\":{\"type\":\"void\",\"x-component\":\"Card\",\"x-component-props\":{\"title\":\"\\u6279\\u91cf\\u53d1\\u653e\\u6a21\\u7248\\u4e0b\\u8f7d\",\"action\":\"action\",\"position\":\"createArea\",\"drive\":\"mysql\",\"btnForm\":\"text\",\"btnContent\":\"\\u6279\\u91cf\\u53d1\\u653e\\u6a21\\u7248\\u4e0b\\u8f7d\",\"resourceType\":\"static\",\"url\":\"\\\/api\\\/operate\\\/background\\\/custombgccardsend\\\/template\"},\"cardType\":\"url\",\"x-designable-id\":\"kz1j0vuqxsf\",\"x-index\":3},\"zh5ufw8veac\":{\"type\":\"void\",\"x-component\":\"Card\",\"x-component-props\":{\"title\":\"\\u6279\\u91cf\\u53d1\\u653e\",\"action\":\"action\",\"position\":\"createArea\",\"drive\":\"mysql\",\"btnForm\":\"text\",\"btnContent\":\"\\u6279\\u91cf\\u53d1\\u653e\",\"width\":640,\"upload_data_type\":\"csv\",\"url\":\"\\\/operate\\\/background\\\/custombgccardsend\\\/batchSend\"},\"cardType\":\"modal\",\"x-designable-id\":\"zh5ufw8veac\",\"x-index\":4,\"width\":640,\"properties\":{\"csv\":{\"title\":\"Csv\",\"title_en\":\"\",\"x-decorator\":\"FormItem\",\"x-component\":\"UploadFile\",\"name\":\"csv\",\"x-designable-id\":\"jdtp0cf5ua4\",\"x-index\":0,\"type\":\"Array<object>\",\"hidden\":0,\"disabled\":0,\"required\":1,\"placeholder\":\"\",\"length\":255,\"x-component-props\":{\"textContent\":\"Upload\"}},\"can_transfer\":{\"title\":\"\\u662f\\u5426\\u53ef\\u8d60\\u9001\",\"title_en\":\"\",\"x-decorator\":\"FormItem\",\"x-component\":\"Select\",\"name\":\"can_transfer\",\"x-designable-id\":\"zxarn0u8byv\",\"x-index\":1,\"type\":\"\",\"hidden\":0,\"disabled\":0,\"required\":0,\"default\":\"1\",\"placeholder\":\"\",\"length\":1,\"enum\":[{\"children\":[],\"label\":\"\\u662f\",\"value\":\"1\"},{\"children\":[],\"label\":\"\\u5426\",\"value\":\"0\"}]}}}},\"x-designable-id\":\"4dacas4lnpc\"}}","guid":"custombgccardsend","model":"","table_config":"{\"fields\":{\"id\":{\"type\":\"int\",\"length\":10,\"default\":null,\"component\":\"numberpicker\",\"comment\":\"序号\",\"comment_en\":\"\"},\"uid\":{\"type\":\"varchar\",\"length\":255,\"default\":null,\"component\":\"input\",\"comment\":\"UID\",\"comment_en\":\"\"},\"big_area_id\":{\"type\":\"varchar\",\"length\":255,\"default\":null,\"component\":\"select\",\"comment\":\"大区\",\"comment_en\":\"\"},\"num\":{\"type\":\"varchar\",\"length\":255,\"default\":null,\"component\":\"input\",\"comment\":\"背景卡数量\",\"comment_en\":\"\"},\"card_type\":{\"type\":\"varchar\",\"length\":255,\"default\":null,\"component\":\"select\",\"comment\":\"类型\",\"comment_en\":\"\"},\"valid_term\":{\"type\":\"varchar\",\"length\":255,\"default\":null,\"component\":\"input\",\"comment\":\"单张背景卡有效期（天）\",\"comment_en\":\"\"},\"can_transfer\":{\"type\":\"tinyint\",\"length\":1,\"default\":null,\"component\":\"select\",\"comment\":\"是否可赠送\",\"comment_en\":\"\"},\"reason\":{\"type\":\"varchar\",\"length\":255,\"default\":null,\"component\":\"input\",\"comment\":\"发放理由\",\"comment_en\":\"\"},\"operator\":{\"type\":\"varchar\",\"length\":255,\"default\":null,\"component\":\"input\",\"comment\":\"操作人\",\"comment_en\":\"\"},\"dateline\":{\"type\":\"int\",\"length\":10,\"default\":null,\"component\":\"datepicker\",\"comment\":\"操作时间\",\"comment_en\":\"\"},\"csv\":{\"type\":\"varchar\",\"length\":255,\"default\":null,\"component\":\"uploadfile\",\"comment\":\"Csv\",\"comment_en\":\"\"}},\"pk\":\"id\",\"visible\":[],\"disable\":[],\"data\":[],\"value\":[],\"comment\":\"自定义背景卡下发\",\"comment_en\":\"\"}","system_id":4}],"Imee\\Models\\Cms\\Lesscode\\LesscodeSchemaPoint":[{"id":22183,"guid":"custombgccardsend","title":"列表","type":"list","drive":"mysql","state":1,"is_system":0,"logic":"","create_time":1755592795,"update_time":0,"system_id":4},{"id":22184,"guid":"custombgccardsend","title":"发放","type":"action","drive":"mysql","state":1,"is_system":0,"logic":"","create_time":1755592795,"update_time":0,"system_id":4},{"id":22185,"guid":"custombgccardsend","title":"批量发放模版下载","type":"action","drive":"mysql","state":1,"is_system":0,"logic":"","create_time":1755592795,"update_time":0,"system_id":4},{"id":22186,"guid":"custombgccardsend","title":"批量发放","type":"action","drive":"mysql","state":1,"is_system":0,"logic":"","create_time":1755592795,"update_time":0,"system_id":4}],"Imee\\Models\\Cms\\Lesscode\\LesscodeSchemaPointConfig":[{"id":22183,"guid":"custombgccardsend","point_id":22183,"config":"{\"list\":{\"id\":{\"component\":\"numberpicker\",\"hidden\":0,\"required\":0,\"disabled\":0,\"comment\":\"\\u5e8f\\u53f7\",\"commentEn\":\"\",\"placeholder\":\"\"},\"uid\":{\"component\":\"input\",\"hidden\":0,\"required\":0,\"disabled\":0,\"comment\":\"UID\",\"commentEn\":\"\",\"placeholder\":\"\"},\"big_area_id\":{\"component\":\"select\",\"hidden\":0,\"required\":0,\"disabled\":0,\"enum\":[],\"func\":{\"service\":\"\\\\Imee\\\\Service\\\\StatusService\",\"method\":\"getFamilyBigArea\",\"params\":[null,\"label,value\"]},\"comment\":\"\\u5927\\u533a\",\"commentEn\":\"\",\"placeholder\":\"\"},\"num\":{\"component\":\"input\",\"hidden\":0,\"required\":0,\"disabled\":0,\"comment\":\"\\u80cc\\u666f\\u5361\\u6570\\u91cf\",\"commentEn\":\"\",\"placeholder\":\"\"},\"card_type\":{\"component\":\"select\",\"hidden\":0,\"required\":0,\"disabled\":0,\"enum\":[],\"func\":{\"service\":\"Imee\\\\Service\\\\Operate\\\\Background\\\\Custombackground\\\\CustomBgcCardSendService\",\"method\":\"getCardTypeMap\",\"params\":[null,\"label,value\"]},\"comment\":\"\\u7c7b\\u578b\",\"commentEn\":\"\",\"placeholder\":\"\"},\"valid_term\":{\"component\":\"input\",\"hidden\":0,\"required\":0,\"disabled\":0,\"style\":{\"width\":200},\"comment\":\"\\u5355\\u5f20\\u80cc\\u666f\\u5361\\u6709\\u6548\\u671f\\uff08\\u5929\\uff09\",\"commentEn\":\"\",\"placeholder\":\"\"},\"can_transfer\":{\"component\":\"select\",\"hidden\":0,\"required\":0,\"disabled\":0,\"enum\":[[\"\\u662f\",\"1\"],[\"\\u5426\",\"0\"]],\"func\":[],\"comment\":\"\\u662f\\u5426\\u53ef\\u8d60\\u9001\",\"commentEn\":\"\",\"placeholder\":\"\"},\"reason\":{\"component\":\"input\",\"hidden\":0,\"required\":0,\"disabled\":0,\"comment\":\"\\u53d1\\u653e\\u7406\\u7531\",\"commentEn\":\"\",\"placeholder\":\"\"},\"operator\":{\"component\":\"input\",\"hidden\":0,\"required\":0,\"disabled\":0,\"comment\":\"\\u64cd\\u4f5c\\u4eba\",\"commentEn\":\"\",\"placeholder\":\"\"},\"dateline\":{\"component\":\"datepicker\",\"hidden\":0,\"required\":0,\"disabled\":0,\"single\":true,\"comment\":\"\\u64cd\\u4f5c\\u65f6\\u95f4\",\"commentEn\":\"\",\"placeholder\":\"\",\"dateFormat\":\"Y-m-d\"}},\"filter\":{\"uid\":{\"component\":\"input\",\"placeholder\":\"\",\"comment\":\"UID\"},\"big_area_id\":{\"component\":\"select\",\"enum\":[],\"func\":{\"service\":\"\\\\Imee\\\\Service\\\\StatusService\",\"method\":\"getFamilyBigArea\",\"params\":[null,\"label,value\"]},\"placeholder\":\"\",\"comment\":\"\\u5927\\u533a\"},\"dateline_sdate\":{\"symbol\":\"egt\",\"component\":\"datepicker.rangepicker\",\"single\":0,\"flag\":\"date\",\"placeholder\":\"\",\"comment\":\"\\u64cd\\u4f5c\\u65f6\\u95f4\"},\"dateline_edate\":{\"symbol\":\"elt\",\"component\":\"datepicker.rangepicker\",\"single\":0,\"flag\":\"date\",\"placeholder\":\"\",\"comment\":\"\\u64cd\\u4f5c\\u65f6\\u95f4\"},\"card_type\":{\"component\":\"select\",\"enum\":[],\"func\":{\"service\":\"Imee\\\\Service\\\\Operate\\\\Background\\\\Custombackground\\\\CustomBgcCardSendService\",\"method\":\"getCardTypeMap\",\"params\":[null,\"label,value\"]},\"placeholder\":\"\",\"comment\":\"\\u7c7b\\u578b\"}}}","create_time":1755592795,"update_time":0,"system_id":4},{"id":22184,"guid":"custombgccardsend","point_id":22184,"config":"{\"type\":\"modal\",\"fields\":{\"uid\":{\"component\":\"input\",\"hidden\":0,\"required\":1,\"disabled\":0,\"comment\":\"UID\",\"commentEn\":\"\",\"placeholder\":\"\"},\"num\":{\"component\":\"input\",\"hidden\":0,\"required\":1,\"disabled\":0,\"comment\":\"\\u6570\\u91cf\",\"commentEn\":\"\",\"placeholder\":\"\"},\"card_type\":{\"component\":\"select\",\"hidden\":0,\"required\":1,\"disabled\":0,\"enum\":[],\"func\":{\"service\":\"Imee\\\\Service\\\\Operate\\\\Background\\\\Custombackground\\\\CustomBgcCardSendService\",\"method\":\"getCardTypeMap\",\"params\":[null,\"label,value\"]},\"comment\":\"\\u7c7b\\u578b\",\"commentEn\":\"\",\"placeholder\":\"\"},\"valid_term\":{\"component\":\"input\",\"hidden\":0,\"required\":1,\"disabled\":0,\"style\":{\"width\":200},\"comment\":\"\\u5355\\u5f20\\u6709\\u6548\\u671f\\uff08\\u5929\\uff09\",\"commentEn\":\"\",\"placeholder\":\"\"},\"can_transfer\":{\"component\":\"select\",\"hidden\":0,\"required\":0,\"disabled\":0,\"enum\":[[\"\\u662f\",\"1\"],[\"\\u5426\",\"0\"]],\"func\":[],\"default\":\"1\",\"comment\":\"\\u662f\\u5426\\u53ef\\u8d60\\u9001\",\"commentEn\":\"\",\"placeholder\":\"\"},\"reason\":{\"component\":\"input.textarea\",\"hidden\":0,\"required\":1,\"disabled\":0,\"comment\":\"\\u53d1\\u653e\\u7406\\u7531\",\"commentEn\":\"\",\"placeholder\":\"\"}},\"url\":\"\\\/operate\\\/background\\\/custombgccardsend\\\/send\",\"width\":640,\"modalTitle\":\"\\u53d1\\u653e\",\"modalTitleEn\":\"\",\"title\":\"\\u53d1\\u653e\",\"title_en\":\"\"}","create_time":1755592795,"update_time":0,"system_id":4},{"id":22185,"guid":"custombgccardsend","point_id":22185,"config":"{\"type\":\"url\",\"path\":\"\\\/api\\\/operate\\\/background\\\/custombgccardsend\\\/template\",\"resourceType\":\"static\",\"modalTitle\":\"\\u6279\\u91cf\\u53d1\\u653e\\u6a21\\u7248\\u4e0b\\u8f7d\",\"modalTitleEn\":\"\",\"title\":\"\\u6279\\u91cf\\u53d1\\u653e\\u6a21\\u7248\\u4e0b\\u8f7d\",\"title_en\":\"\"}","create_time":1755592795,"update_time":0,"system_id":4},{"id":22186,"guid":"custombgccardsend","point_id":22186,"config":"{\"type\":\"modal\",\"fields\":{\"csv\":{\"component\":\"uploadfile\",\"hidden\":0,\"required\":1,\"disabled\":0,\"comment\":\"Csv\",\"commentEn\":\"\",\"placeholder\":\"\"},\"can_transfer\":{\"component\":\"select\",\"hidden\":0,\"required\":0,\"disabled\":0,\"enum\":[[\"\\u662f\",\"1\"],[\"\\u5426\",\"0\"]],\"func\":[],\"default\":\"1\",\"comment\":\"\\u662f\\u5426\\u53ef\\u8d60\\u9001\",\"commentEn\":\"\",\"placeholder\":\"\"}},\"url\":\"\\\/operate\\\/background\\\/custombgccardsend\\\/batchSend\",\"width\":640,\"upload_data_type\":\"csv\",\"modalTitle\":\"\\u6279\\u91cf\\u53d1\\u653e\",\"modalTitleEn\":\"\",\"title\":\"\\u6279\\u91cf\\u53d1\\u653e\",\"title_en\":\"\"}","create_time":1755592795,"update_time":0,"system_id":4}]}